{"_ts":[1557718450,1557722685],"_r":{"breakdown":{"html":{"bytes":[77082,77105],"requests":[1,2]},"js":{"bytes":[462967,462967],"requests":[24,24]},"css":{"bytes":[39931,39931],"requests":[7,7]},"image":{"bytes":[355034,355034],"requests":[47,47]},"flash":{"bytes":[0,0],"requests":[0,0]},"font":{"bytes":[132844,132844],"requests":[3,3]},"video":{"bytes":[0,0],"requests":[0,0]},"other":{"bytes":[1645,2372],"requests":[4,5]}},"date":[1557718450,1557722685],"domElements":[2535,2535],"domInteractive":[1042,1018.2],"firstPaint":[849.22499999998,842.3310000000199],"fullyLoaded":[2853.6,2696.6],"id":["190512_N2_ca8efe23eed43430e39199e7f1accfa7","190512_S2_30327ccbea3dda66ae52ba49d1f1d709"],"loadTime":[2077.4,1975.2],"render":[820,900],"SpeedIndex":[1233.6,1241.6],"TTFB":[344,324],"videoFrames":[[{"_i":"ms_000000.jpg","_t":0,"_vc":0},{"_i":"ms_000800.jpg","_t":800,"_vc":8},{"_i":"ms_001000.jpg","_t":1000,"_vc":74},{"_i":"ms_001100.jpg","_t":1100,"_vc":75},{"_i":"ms_001200.jpg","_t":1200,"_vc":77},{"_i":"ms_001300.jpg","_t":1300,"_vc":85},{"_i":"ms_001500.jpg","_t":1500,"_vc":89},{"_i":"ms_001600.jpg","_t":1600,"_vc":88},{"_i":"ms_001800.jpg","_t":1800,"_vc":89},{"_i":"ms_002000.jpg","_t":2000,"_vc":89},{"_i":"ms_002300.jpg","_t":2300,"_vc":89},{"_i":"ms_002400.jpg","_t":2400,"_vc":89},{"_i":"ms_002500.jpg","_t":2500,"_vc":100},{"_i":"ms_002600.jpg","_t":2600,"_vc":100},{"_i":"ms_002700.jpg","_t":2700,"_vc":100}],[{"_i":"ms_000000.jpg","_t":0,"_vc":0},{"_i":"ms_001000.jpg","_t":1000,"_vc":8},{"_i":"ms_001100.jpg","_t":1100,"_vc":8},{"_i":"ms_001200.jpg","_t":1200,"_vc":73},{"_i":"ms_001300.jpg","_t":1300,"_vc":74},{"_i":"ms_001400.jpg","_t":1400,"_vc":74},{"_i":"ms_001500.jpg","_t":1500,"_vc":74},{"_i":"ms_001700.jpg","_t":1700,"_vc":89},{"_i":"ms_001800.jpg","_t":1800,"_vc":89},{"_i":"ms_002400.jpg","_t":2400,"_vc":100},{"_i":"ms_002500.jpg","_t":2500,"_vc":100}]],"visualComplete":[2520,2440],"lighthouse":[65,65],"pagespeed":[83,83]}}